guess_the_number/guess_the_number/__init__.py
guess_the_number/guess_the_number/game.py
my_eldar_guess_the_number_game-1.0.2.dist-info/METADATA
my_eldar_guess_the_number_game-1.0.2.dist-info/WHEEL
my_eldar_guess_the_number_game-1.0.2.dist-info/top_level.txt
my_eldar_guess_the_number_game-1.0.2.dist-info/RECORD
