Metadata-Version: 2.4
Name: my-eldar-guess-the-number-game
Version: 1.0.2
Summary: Simple guess the number game
Author-email: Eldar <eldaraliyev675@gmail.com>
License: MIT
Classifier: Programming Language :: Python :: 3
Classifier: License :: OSI Approved :: MIT License
Classifier: Operating System :: OS Independent
Requires-Python: >=3.8
